docqa_bench/__init__.py
docqa_bench/benchmark.py
docqa_bench/chunkers/simple_chunker.py
docqa_bench/cli/main.py
docqa_bench/core/answer_generator.py
docqa_bench/core/chunker.py
docqa_bench/core/document.py
docqa_bench/core/embedder.py
docqa_bench/core/evaluator.py
docqa_bench/core/question_generator.py
docqa_bench/core/vector_store.py
docqa_bench/embedders/openai_embedder.py
docqa_bench/metrics/f1_score.py
docqa_bench/models/openai_model.py
docqa_bench/vector_stores/chroma_store.py
docqa_bench-0.1.13.dist-info/LICENSE
docqa_bench-0.1.13.dist-info/METADATA
docqa_bench-0.1.13.dist-info/WHEEL
docqa_bench-0.1.13.dist-info/RECORD
