Metadata-Version: 2.1
Name: docqa-bench
Version: 0.1.13
Summary: A library for benchmarking document QA systems
Home-page: https://github.com/JoshuaOliphant/docqa_bench
License: MIT
Author: Joshua Oliphant
Author-email: joshua.oliphant@hey.com
Requires-Python: >=3.10.1,<4.0.0
Classifier: License :: OSI Approved :: MIT License
Classifier: Programming Language :: Python :: 3
Classifier: Programming Language :: Python :: 3.11
Classifier: Programming Language :: Python :: 3.12
Requires-Dist: aiofiles (>=24.1.0,<25.0.0)
Requires-Dist: chromadb (>=0.5.3,<0.6.0)
Requires-Dist: flake8 (>=7.1.0,<8.0.0)
Requires-Dist: langchain (>=0.2.6,<0.3.0)
Requires-Dist: openai (==1.35.10)
Requires-Dist: opentelemetry-api (>=1.22.0,<2.0.0)
Requires-Dist: opentelemetry-exporter-otlp (>=1.22.0,<2.0.0)
Requires-Dist: opentelemetry-sdk (>=1.22.0,<2.0.0)
Requires-Dist: protobuf (>=3.19,<5.0)
Requires-Dist: pydantic (>=2.8.2,<3.0.0)
Requires-Dist: scikit-learn (>=1.0.2,<2.0.0)
Project-URL: Repository, https://github.com/JoshuaOliphant/docqa_bench
